LICENSE.txt
README.md
setup.cfg
setup.py
os_android_package_name_changer/name_changer.py
os_android_package_name_changer.egg-info/PKG-INFO
os_android_package_name_changer.egg-info/SOURCES.txt
os_android_package_name_changer.egg-info/dependency_links.txt
os_android_package_name_changer.egg-info/requires.txt
os_android_package_name_changer.egg-info/top_level.txt
os_android_package_name_changer/bp/_name_changer_boilerplate.py