Metadata-Version: 2.1
Name: os_android_package_name_changer
Version: 1.13
Summary: will change the package name of an android app programmatically (dynamically)
Home-page: https://github.com/osfunapps/os-android-version-changer-py
Author: Oz Shabat
Author-email: osfunapps@gmail.com
License: MIT
Keywords: python,osfunapps,android,package,automation
Classifier: Development Status :: 5 - Production/Stable
Classifier: Intended Audience :: Developers
Classifier: Topic :: Software Development :: Build Tools
Classifier: License :: OSI Approved :: MIT License
Classifier: Programming Language :: Python :: 3
Classifier: Programming Language :: Python :: 3.4
Classifier: Programming Language :: Python :: 3.5
Classifier: Programming Language :: Python :: 3.6
Classifier: Programming Language :: Python :: 3.9
License-File: LICENSE.txt
Requires-Dist: os_tools
Requires-Dist: os_file_handler
Requires-Dist: os_file_stream_handler
